eventor_py/__init__.py
tests/__init__.py
tests/test.py
tests/testParse.py
tests/test_parse_files.py
eventor_py-0.0.1.dist-info/METADATA
eventor_py-0.0.1.dist-info/WHEEL
eventor_py-0.0.1.dist-info/top_level.txt
eventor_py-0.0.1.dist-info/RECORD
